{
"type": "FeatureCollection",
"name": "quartier_touba_centroid",
"crs": { "type": "name", "properties": { "name": "urn:ogc:def:crs:OGC:1.3:CRS84" } },
"features": [
{ "type": "Feature", "properties": { "QRT_VLG_HA": "SAM LAH", "Enquete": "OUI" }, "geometry": { "type": "Point", "coordinates": [ -15.915031840676409, 14.877709698994302 ] } },
{ "type": "Feature", "properties": { "QRT_VLG_HA": "MADIYANA", "Enquete": "OUI" }, "geometry": { "type": "Point", "coordinates": [ -15.904973013246538, 14.881258207038798 ] } },
{ "type": "Feature", "properties": { "QRT_VLG_HA": "DIAHNATOUL MAHWA", "Enquete": "OUI" }, "geometry": { "type": "Point", "coordinates": [ -15.912626662913928, 14.858023424146026 ] } },
{ "type": "Feature", "properties": { "QRT_VLG_HA": "NDINDY ABDOU", "Enquete": "OUI" }, "geometry": { "type": "Point", "coordinates": [ -15.819539052263812, 14.873948278694929 ] } },
{ "type": "Feature", "properties": { "QRT_VLG_HA": "TINDODY", "Enquete": "OUI" }, "geometry": { "type": "Point", "coordinates": [ -15.843879561846888, 14.894628236320742 ] } },
{ "type": "Feature", "properties": { "QRT_VLG_HA": "GOUYE MBIND", "Enquete": "OUI" }, "geometry": { "type": "Point", "coordinates": [ -15.851983725505999, 14.867681097021389 ] } },
{ "type": "Feature", "properties": { "QRT_VLG_HA": "BAGDAD", "Enquete": "OUI" }, "geometry": { "type": "Point", "coordinates": [ -15.86366264607809, 14.926736576693497 ] } },
{ "type": "Feature", "properties": { "QRT_VLG_HA": "DAROU KHOUDOSS", "Enquete": "OUI" }, "geometry": { "type": "Point", "coordinates": [ -15.874881845254793, 14.876307597067166 ] } },
{ "type": "Feature", "properties": { "QRT_VLG_HA": "DAROU MARNANE", "Enquete": "OUI" }, "geometry": { "type": "Point", "coordinates": [ -15.883388202151382, 14.833566746023944 ] } },
{ "type": "Feature", "properties": { "QRT_VLG_HA": "GUEDE BOUSSO", "Enquete": "OUI" }, "geometry": { "type": "Point", "coordinates": [ -15.869881006573417, 14.895315373272551 ] } },
{ "type": "Feature", "properties": { "QRT_VLG_HA": "KEUR NIANG", "Enquete": "OUI" }, "geometry": { "type": "Point", "coordinates": [ -15.8706539248259, 14.845690161643541 ] } },
{ "type": "Feature", "properties": { "QRT_VLG_HA": "NDINDY", "Enquete": "OUI" }, "geometry": { "type": "Point", "coordinates": [ -15.811017244695931, 14.892727197520784 ] } },
{ "type": "Feature", "properties": { "QRT_VLG_HA": "TOUBA HLM", "Enquete": "OUI" }, "geometry": { "type": "Point", "coordinates": [ -15.896331685847178, 14.898397042270716 ] } },
{ "type": "Feature", "properties": { "QRT_VLG_HA": "DAROU MINAM", "Enquete": "OUI" }, "geometry": { "type": "Point", "coordinates": [ -15.899069627066233, 14.851686929672523 ] } },
{ "type": "Feature", "properties": { "QRT_VLG_HA": "TOUBA MOSQUEE", "Enquete": "OUI" }, "geometry": { "type": "Point", "coordinates": [ -15.839523494955792, 14.848031470941017 ] } },
{ "type": "Feature", "properties": { "QRT_VLG_HA": "DAROU RAHMANE", "Enquete": "OUI" }, "geometry": { "type": "Point", "coordinates": [ -15.846787277417626, 14.83486058448435 ] } }
]
}
